Metadata-Version: 2.1
Name: commscores
Version: 0.0.10
Summary: A Python package for quantifying microbial interactions
Home-page: https://github.com/freiburgermsu/CommScores
Author: Andrew Freiburger
Author-email: andrewfreiburger@gmail.com
License: MIT License
Project-URL: Documentation, https://commscores.readthedocs.io/en/latest/
Project-URL: Issues, https://github.com/freiburgermsu/CommScores/issues
Keywords: microbiology,community,scores,interaction,syntrophy,competition
Platform: UNKNOWN
Classifier: Topic :: Scientific/Engineering :: Bio-Informatics
Classifier: Intended Audience :: Science/Research
Classifier: Operating System :: OS Independent
Classifier: Programming Language :: Python :: 3.8
Classifier: Programming Language :: Python :: 3.9
Classifier: Programming Language :: Python :: 3.10
Classifier: Programming Language :: Python :: 3.11
Classifier: Natural Language :: English
License-File: LICENSE
